aws_recommendation_a17/__init__.py
aws_recommendation_a17/cloudwatch.py
aws_recommendation_a17/cost_estimations.py
aws_recommendation_a17/dynamodb.py
aws_recommendation_a17/ebs.py
aws_recommendation_a17/ec2.py
aws_recommendation_a17/elb.py
aws_recommendation_a17/kms.py
aws_recommendation_a17/rds.py
aws_recommendation_a17/recommendation.py
aws_recommendation_a17/redshift.py
aws_recommendation_a17/s3.py
aws_recommendation_a17/truted_advisor.py
aws_recommendation_a17/utils.py
aws_recommendation_a17-0.1.2.dist-info/LICENCE
aws_recommendation_a17-0.1.2.dist-info/METADATA
aws_recommendation_a17-0.1.2.dist-info/WHEEL
aws_recommendation_a17-0.1.2.dist-info/top_level.txt
aws_recommendation_a17-0.1.2.dist-info/RECORD
